atomicfile.py
atomicfile-1.0.1.dist-info/LICENSE.rst
atomicfile-1.0.1.dist-info/METADATA
atomicfile-1.0.1.dist-info/WHEEL
atomicfile-1.0.1.dist-info/top_level.txt
atomicfile-1.0.1.dist-info/RECORD
