Metadata-Version: 2.1
Name: atomicfile
Version: 1.0.1
Summary: Writeable file object that atomically updates a file.
Home-page: http://github.com/sashka/atomicfile-py
Author: Alexander Saltanov
Author-email: asd@mokote.com
License: MIT
Platform: UNKNOWN
Classifier: Intended Audience :: Developers
Classifier: Intended Audience :: System Administrators
Classifier: Operating System :: OS Independent
Classifier: Topic :: Software Development
